<?xml version="1.0" encoding="utf-8" ?>
<Defs>

	<SoundDef ParentName = "AK_VoiceBase">
        <defName>AK_Voice_Recruit_Warfarin</defName>
        <subSounds>
            <li>
                <onCamera>True</onCamera>
                <grains>
                    <li Class="AudioGrain_Clip">
                        <clipPath>Operator/Medic/Warfarin/char_171_bldsk/Recruit_Warfarin</clipPath>
                    </li>
                </grains>
                <volumeRange>40~40</volumeRange>
                <distRange>10~100</distRange>
                <sustainLoop>False</sustainLoop>
            </li>
        </subSounds>
    </SoundDef>

    <SoundDef ParentName = "AK_VoiceBase">
        <defName>AK_Voice_Die_Warfarin</defName>
        <subSounds>
            <li>
                <onCamera>True</onCamera>
                <grains>
                    <li Class="AudioGrain_Clip">
                        <clipPath>Operator/Medic/Warfarin/char_171_bldsk/Die_Warfarin</clipPath>
                    </li>
                </grains>
                <volumeRange>40~40</volumeRange>
                <distRange>10~100</distRange>
                <sustainLoop>False</sustainLoop>
            </li>
        </subSounds>
    </SoundDef>

    <SoundDef ParentName = "AK_VoiceBase">
        <defName>AK_Voice_Draft_WarfarinI</defName>
        <subSounds>
            <li>
                <onCamera>True</onCamera>
                <grains>
                    <li Class="AudioGrain_Clip">
                        <clipPath>Operator/Medic/Warfarin/char_171_bldsk/Draft_WarfarinI</clipPath>
                    </li>
                </grains>
                <volumeRange>40~40</volumeRange>
                <distRange>10~100</distRange>
                <sustainLoop>False</sustainLoop>
            </li>
        </subSounds>
    </SoundDef>

    <SoundDef ParentName = "AK_VoiceBase">
        <defName>AK_Voice_Draft_WarfarinII</defName>
        <subSounds>
            <li>
                <onCamera>True</onCamera>
                <grains>
                    <li Class="AudioGrain_Clip">
                        <clipPath>Operator/Medic/Warfarin/char_171_bldsk/Draft_WarfarinII</clipPath>
                    </li>
                </grains>
                <volumeRange>40~40</volumeRange>
                <distRange>10~100</distRange>
                <sustainLoop>False</sustainLoop>
            </li>
        </subSounds>
    </SoundDef>

    <SoundDef ParentName = "AK_VoiceBase">
        <defName>AK_Voice_Select_WarfarinI</defName>
        <subSounds>
            <li>
                <onCamera>True</onCamera>
                <grains>
                    <li Class="AudioGrain_Clip">
                        <clipPath>Operator/Medic/Warfarin/char_171_bldsk/Select_WarfarinI</clipPath>
                    </li>
                </grains>
                <volumeRange>40~40</volumeRange>
                <distRange>10~100</distRange>
                <sustainLoop>False</sustainLoop>
            </li>
        </subSounds>
    </SoundDef>

    <SoundDef ParentName = "AK_VoiceBase">
        <defName>AK_Voice_Select_WarfarinII</defName>
        <subSounds>
            <li>
                <onCamera>True</onCamera>
                <grains>
                    <li Class="AudioGrain_Clip">
                        <clipPath>Operator/Medic/Warfarin/char_171_bldsk/Select_WarfarinII</clipPath>
                    </li>
                </grains>
                <volumeRange>40~40</volumeRange>
                <distRange>10~100</distRange>
                <sustainLoop>False</sustainLoop>
            </li>
        </subSounds>
    </SoundDef>

    <SoundDef ParentName = "AK_VoiceBase">
        <defName>AK_Voice_Select_WarfarinIII</defName>
        <subSounds>
            <li>
                <onCamera>True</onCamera>
                <grains>
                    <li Class="AudioGrain_Clip">
                        <clipPath>Operator/Medic/Warfarin/char_171_bldsk/Select_WarfarinIII</clipPath>
                    </li>
                </grains>
                <volumeRange>40~40</volumeRange>
                <distRange>10~100</distRange>
                <sustainLoop>False</sustainLoop>
            </li>
        </subSounds>
    </SoundDef>

    <SoundDef ParentName = "AK_VoiceBase">
        <defName>AK_Voice_Select_WarfarinIV</defName>
        <subSounds>
            <li>
                <onCamera>True</onCamera>
                <grains>
                    <li Class="AudioGrain_Clip">
                        <clipPath>Operator/Medic/Warfarin/char_171_bldsk/Select_WarfarinIV</clipPath>
                    </li>
                </grains>
                <volumeRange>40~40</volumeRange>
                <distRange>10~100</distRange>
                <sustainLoop>False</sustainLoop>
            </li>
        </subSounds>
    </SoundDef>

    <SoundDef ParentName = "AK_VoiceBase">
        <defName>AK_Voice_Ability_WarfarinI</defName>
        <subSounds>
            <li>
                <onCamera>True</onCamera>
                <grains>
                    <li Class="AudioGrain_Clip">
                        <clipPath>Operator/Medic/Warfarin/char_171_bldsk/Ability_WarfarinI</clipPath>
                    </li>
                </grains>
                <volumeRange>40~40</volumeRange>
                <distRange>10~100</distRange>
                <sustainLoop>False</sustainLoop>
            </li>
        </subSounds>
    </SoundDef>

    <SoundDef ParentName = "AK_VoiceBase">
        <defName>AK_Voice_Ability_WarfarinII</defName>
        <subSounds>
            <li>
                <onCamera>True</onCamera>
                <grains>
                    <li Class="AudioGrain_Clip">
                        <clipPath>Operator/Medic/Warfarin/char_171_bldsk/Ability_WarfarinII</clipPath>
                    </li>
                </grains>
                <volumeRange>40~40</volumeRange>
                <distRange>10~100</distRange>
                <sustainLoop>False</sustainLoop>
            </li>
        </subSounds>
    </SoundDef>

    <SoundDef ParentName = "AK_VoiceBase">
        <defName>AK_Voice_Ability_WarfarinIII</defName>
        <subSounds>
            <li>
                <onCamera>True</onCamera>
                <grains>
                    <li Class="AudioGrain_Clip">
                        <clipPath>Operator/Medic/Warfarin/char_171_bldsk/Ability_WarfarinIII</clipPath>
                    </li>
                </grains>
                <volumeRange>40~40</volumeRange>
                <distRange>10~100</distRange>
                <sustainLoop>False</sustainLoop>
            </li>
        </subSounds>
    </SoundDef>

    <SoundDef ParentName = "AK_VoiceBase">
        <defName>AK_Voice_Ability_WarfarinIV</defName>
        <subSounds>
            <li>
                <onCamera>True</onCamera>
                <grains>
                    <li Class="AudioGrain_Clip">
                        <clipPath>Operator/Medic/Warfarin/char_171_bldsk/Ability_WarfarinIV</clipPath>
                    </li>
                </grains>
                <volumeRange>40~40</volumeRange>
                <distRange>10~100</distRange>
                <sustainLoop>False</sustainLoop>
            </li>
        </subSounds>
    </SoundDef>

    <SoundDef ParentName = "AK_VoiceBase">
        <defName>AK_Voice_Undraft_Warfarin</defName>
        <subSounds>
            <li>
                <onCamera>True</onCamera>
                <grains>
                    <li Class="AudioGrain_Clip">
                        <clipPath>Operator/Medic/Warfarin/char_171_bldsk/Undraft_Warfarin</clipPath>
                    </li>
                </grains>
                <volumeRange>40~40</volumeRange>
                <distRange>10~100</distRange>
                <sustainLoop>False</sustainLoop>
            </li>
        </subSounds>
    </SoundDef>
	
</Defs>