<?xml version="1.0" encoding="utf-8" ?>
<Defs>

	<IdeoIconDef>
		<defName>AK_IdeoIcon_Victoria</defName>
		<iconPath>Things/Ideology/Victoria</iconPath>
	</IdeoIconDef>

	<IdeoIconDef>
		<defName>AK_IdeoIcon_Agir</defName>
		<iconPath>Things/Ideology/Agir</iconPath>
	</IdeoIconDef>

	<IdeoIconDef>
		<defName>AK_IdeoIcon_Colombia</defName>
		<iconPath>Things/Ideology/Colombia</iconPath>
	</IdeoIconDef>

	<IdeoIconDef>
		<defName>AK_IdeoIcon_Deepsea</defName>
		<iconPath>Things/Ideology/Deepsea</iconPath>
	</IdeoIconDef>

	<IdeoIconDef>
		<defName>AK_IdeoIcon_Higashi</defName>
		<iconPath>Things/Ideology/Higashi</iconPath>
	</IdeoIconDef>

	<IdeoIconDef>
		<defName>AK_IdeoIcon_Karlan</defName>
		<iconPath>Things/Ideology/Karlan</iconPath>
	</IdeoIconDef>

	<IdeoIconDef>
		<defName>AK_IdeoIcon_Lees</defName>
		<iconPath>Things/Ideology/Lees</iconPath>
	</IdeoIconDef>

	<IdeoIconDef>
		<defName>AK_IdeoIcon_Minos</defName>
		<iconPath>Things/Ideology/Minos</iconPath>
	</IdeoIconDef>

	<IdeoIconDef>
		<defName>AK_IdeoIcon_Penguin</defName>
		<iconPath>Things/Ideology/Penguin</iconPath>
	</IdeoIconDef>

	<IdeoIconDef>
		<defName>AK_IdeoIcon_RhodesIsland</defName>
		<iconPath>Things/Ideology/RhodesIsland</iconPath>
	</IdeoIconDef>

	<IdeoIconDef>
		<defName>AK_IdeoIcon_RimBilliton</defName>
		<iconPath>Things/Ideology/RimBilliton</iconPath>
	</IdeoIconDef>

	<IdeoIconDef>
		<defName>AK_IdeoIcon_Sami</defName>
		<iconPath>Things/Ideology/Sami</iconPath>
	</IdeoIconDef>

	<IdeoIconDef>
		<defName>AK_IdeoIcon_Siesta</defName>
		<iconPath>Things/Ideology/Siesta</iconPath>
	</IdeoIconDef>

	<IdeoIconDef>
		<defName>AK_IdeoIcon_Siracusa</defName>
		<iconPath>Things/Ideology/Siracusa</iconPath>
	</IdeoIconDef>

	<IdeoIconDef>
		<defName>AK_IdeoIcon_RhineLab</defName>
		<iconPath>Things/Ideology/RhineLab</iconPath>
	</IdeoIconDef>
</Defs>