<?xml version="1.0" encoding="utf-8"?>
<Defs>

	<ThoughtDef ParentName="BA_Thought_Permanent">
		<defName>BA_Thought_Trait_KarinThird</defName>
		<requiredTraits>
			<li>BA_Trait_KarinThird</li>
		</requiredTraits>
		<stages>
			<li>
				<label>笨蛋？</label>
				<description>啊啊...，如果这次考试再不及格的话，那我的代号可能就要从【02】变成【笨蛋】了啊...</description>
				<baseMoodEffect>-2</baseMoodEffect>
			</li>
		</stages>
	</ThoughtDef>

	<ThoughtDef ParentName="BA_Thought_Permanent">
		<defName>BA_Thought_Trait_KarinSecond</defName>
		<requiredTraits>
			<li>BA_Trait_KarinSecond</li>
		</requiredTraits>
		<stages>
			<li>
				<label>闲情雅致</label>
				<description>美丽的地方……我也想有天能变得漂亮…</description>
				<baseMoodEffect>6</baseMoodEffect>
			</li>
		</stages>
	</ThoughtDef>

	<ThoughtDef ParentName="BA_Thought_Permanent">
		<defName>BA_Thought_Trait_Karin</defName>
		<requiredTraits>
			<li>BA_Trait_Karin</li>
		</requiredTraits>
		<stages>
			<li>
				<label>可靠女仆</label>
				<description>虽然我一开始是因为衣服好看才加入女仆部的，但是现在女仆装对我来说已经不止是一件美丽的衣服了，因为这件衣服代表了我愿意为千年奉献的决心。</description>
				<baseMoodEffect>8</baseMoodEffect>
			</li>
		</stages>
	</ThoughtDef>

	<ThoughtDef ParentName="BA_Thought_Permanent">
		<defName>BA_Thought_Trait_AkaneSecond</defName>
		<requiredTraits>
			<li>BA_Trait_AkaneSecond</li>
		</requiredTraits>
		<stages>
			<li>
				<label>清扫高手</label>
				<description>优雅地清除。</description>
				<baseMoodEffect>6</baseMoodEffect>
			</li>
		</stages>
	</ThoughtDef>

	<ThoughtDef ParentName="BA_Thought_Permanent">
		<defName>BA_Thought_Trait_Akane</defName>
		<requiredTraits>
			<li>BA_Trait_Akane</li>
		</requiredTraits>
		<stages>
			<li>
				<label>温柔女仆？</label>
				<description>好，接下来开始侍奉吧。</description>
				<baseMoodEffect>6</baseMoodEffect>
			</li>
		</stages>
	</ThoughtDef>

	<ThoughtDef ParentName="BA_Thought_Permanent">
		<defName>BA_Thought_Trait_TokiSecond</defName>
		<requiredTraits>
			<li>BA_Trait_TokiSecond</li>
		</requiredTraits>
		<stages>
			<li>
				<label>理性</label>
				<description>请不要默不作声……很难为情不是吗……</description>
				<baseMoodEffect>5</baseMoodEffect>
			</li>
		</stages>
	</ThoughtDef>

	<ThoughtDef ParentName="BA_Thought_Permanent">
		<defName>BA_Thought_Trait_Neru</defName>
		<requiredTraits>
			<li>BA_Trait_Neru</li>
		</requiredTraits>
		<stages>
			<li>
				<label>小太妹</label>
				<description>啊？想找死吗？</description>
				<baseMoodEffect>2</baseMoodEffect>
			</li>
		</stages>
	</ThoughtDef>

	<ThoughtDef ParentName="BA_Thought_Permanent">
		<defName>BA_Thought_Trait_ArisSecond</defName>
		<requiredTraits>
			<li>BA_Trait_ArisSecond</li>
		</requiredTraits>
		<stages>
			<li>
				<label>光之勇者</label>
				<description>爱丽丝不觉得基沃托斯没有魔法，魔法是存在的；因为现在爱丽丝感到了幸福。游戏，猫，朋友，还有，现在这个瞬间，这个世界上有很多美丽的东西。</description>
				<baseMoodEffect>15</baseMoodEffect>
			</li>
		</stages>
	</ThoughtDef>

	<ThoughtDef ParentName="BA_Thought_Permanent">
		<defName>BA_Thought_Trait_Yuzu</defName>
		<requiredTraits>
			<li>BA_Trait_Yuzu</li>
		</requiredTraits>
		<stages>
			<li>
				<label>重度社恐</label>
				<description>呜呜，好想躲起来......</description>
				<baseMoodEffect>-6</baseMoodEffect>
			</li>
		</stages>
	</ThoughtDef>

	<ThoughtDef ParentName="BA_Thought_Permanent">
		<defName>BA_Thought_Trait_Momoi</defName>
		<requiredTraits>
			<li>BA_Trait_Momoi</li>
		</requiredTraits>
		<stages>
			<li>
				<label>创作的痛苦</label>
				<description>任务什么的待会再说，总之先来打游戏吧！</description>
				<baseMoodEffect>8</baseMoodEffect>
			</li>
		</stages>
	</ThoughtDef>

	<ThoughtDef ParentName="BA_Thought_Permanent">
		<defName>BA_Thought_Trait_Midori</defName>
		<requiredTraits>
			<li>BA_Trait_Midori</li>
		</requiredTraits>
		<stages>
			<li>
				<label>绘图打磨</label>
				<description>想要创作出更美丽的东西。为此……丰富的经验是不可或缺的。</description>
				<baseMoodEffect>4</baseMoodEffect>
			</li>
		</stages>
	</ThoughtDef>

	<ThoughtDef ParentName="BA_Thought_Permanent">
		<defName>BA_Thought_Trait_Utaha</defName>
		<requiredTraits>
			<li>BA_Trait_Utaha</li>
		</requiredTraits>
		<stages>
			<li>
				<label>热情少女</label>
				<description>不可思议啊，人类的心。虽然不知道是什么样的机制，却能令我心跳加速。</description>
				<baseMoodEffect>5</baseMoodEffect>
			</li>
		</stages>
	</ThoughtDef>

	<ThoughtDef ParentName="BA_Thought_Permanent">
		<defName>BA_Thought_Trait_Rio</defName>
		<requiredTraits>
			<li>BA_Trait_RioSecond</li>
		</requiredTraits>
		<stages>
			<li>
				<label>极端理性主义者</label>
				<description>追求合理才是能带来最高效率的选择</description>
				<baseMoodEffect>-8</baseMoodEffect>
			</li>
		</stages>
	</ThoughtDef>

	<ThoughtDef ParentName="BA_Thought_Permanent">
		<defName>BA_Thought_Trait_Yuuka</defName>
		<requiredTraits>
			<li>BA_Trait_YuukaSecond</li>
		</requiredTraits>
		<stages>
			<li>
				<label>一板一眼？</label>
				<description>需要休息一下吗？我还有1890秒的空闲时间。</description>
				<baseMoodEffect>6</baseMoodEffect>
			</li>
		</stages>
	</ThoughtDef>

</Defs>