<?xml version="1.0" encoding="utf-8" ?>
<Defs>

	<ThingDef ParentName="AK_ArmorBase_OtherLeader">
		<defName>AK_Apparel_Kristen</defName>
		<label>克丽斯腾服装</label>
		<graphicData>
			<texPath>Things/AK_Agents/OtherLeader/Kristen</texPath>
			<graphicClass>Graphic_Single</graphicClass>
		</graphicData>
		<apparel>
			<wornGraphicPath>Things/AK_Agents/OtherLeader/Kristen</wornGraphicPath>
		</apparel>
	</ThingDef>

	<ThingDef ParentName="AK_ArmorBase_OtherLeader">
		<defName>AK_Apparel_FrostNova</defName>
		<label>霜星服装</label>
		<graphicData>
			<texPath>Things/AK_Agents/OtherLeader/FrostNova</texPath>
			<graphicClass>Graphic_Single</graphicClass>
		</graphicData>
		<apparel>
			<wornGraphicPath>Things/AK_Agents/OtherLeader/FrostNova</wornGraphicPath>
		</apparel>
	</ThingDef>

	<ThingDef ParentName="AK_ArmorBase_OtherLeader">
		<defName>AK_Apparel_Eblana</defName>
		<label>爱布拉娜服装</label>
		<graphicData>
			<texPath>Things/AK_Agents/OtherLeader/Eblana</texPath>
			<graphicClass>Graphic_Single</graphicClass>
		</graphicData>
		<apparel>
			<wornGraphicPath>Things/AK_Agents/OtherLeader/Eblana</wornGraphicPath>
		</apparel>
	</ThingDef>

	<ThingDef ParentName="AK_ArmorBase_OtherLeader">
		<defName>AK_Apparel_Administrator</defName>
		<label>管理员服装</label>
		<graphicData>
			<texPath>Things/AK_Agents/OtherLeader/Administrator</texPath>
			<graphicClass>Graphic_Single</graphicClass>
		</graphicData>
		<apparel>
			<wornGraphicPath>Things/AK_Agents/OtherLeader/Administrator</wornGraphicPath>
		</apparel>
	</ThingDef>

	<ThingDef ParentName="AK_ArmorBase_OtherLeader">
		<defName>AK_Apparel_DukeWindermere</defName>
		<label>温德米尔公爵服装</label>
		<graphicData>
			<texPath>Things/AK_Agents/OtherLeader/DukeWindermere</texPath>
			<graphicClass>Graphic_Single</graphicClass>
		</graphicData>
		<apparel>
			<wornGraphicPath>Things/AK_Agents/OtherLeader/DukeWindermere</wornGraphicPath>
		</apparel>
	</ThingDef>

	<ThingDef ParentName="AK_ArmorBase_OtherLeader">
		<defName>AK_Apparel_PRTS</defName>
		<label>普瑞赛斯服装</label>
		<graphicData>
			<texPath>Things/AK_Agents/OtherLeader/PRTS</texPath>
			<graphicClass>Graphic_Single</graphicClass>
		</graphicData>
		<apparel>
			<wornGraphicPath>Things/AK_Agents/OtherLeader/PRTS</wornGraphicPath>
		</apparel>
	</ThingDef>

</Defs>